.dockerignore
.gitattributes
.gitignore
.gitlab-ci.yml
.markdownlint.yaml
.pre-commit-config.yaml
CHANGELOG.md
CONTRIBUTING.md
Dockerfile
LICENSE.txt
MANIFEST.in
Makefile
PhysicsNeMo_overview.png
README.md
SECURITY.md
pyproject.toml
setup.cfg
setup.py
sonar-project.properties
.devcontainer/devcontainer.json
.github/PULL_REQUEST_TEMPLATE.md
.github/ISSUE_TEMPLATE/bug_report.yml
.github/ISSUE_TEMPLATE/config.yml
.github/ISSUE_TEMPLATE/documentation_request.yml
.github/ISSUE_TEMPLATE/feature_request.yml
.github/workflows/blossom-ci.yml
.gitlab/merge_request_templates/Default.md
nvidia_physicsnemo.sym.egg-info/PKG-INFO
nvidia_physicsnemo.sym.egg-info/SOURCES.txt
nvidia_physicsnemo.sym.egg-info/dependency_links.txt
nvidia_physicsnemo.sym.egg-info/requires.txt
nvidia_physicsnemo.sym.egg-info/top_level.txt
physicsnemo/sym/__init__.py
physicsnemo/sym/amp.py
physicsnemo/sym/constants.py
physicsnemo/sym/graph.py
physicsnemo/sym/key.py
physicsnemo/sym/manager.py
physicsnemo/sym/node.py
physicsnemo/sym/trainer.py
physicsnemo/sym/csrc/AmpKernels.cu
physicsnemo/sym/dataset/__init__.py
physicsnemo/sym/dataset/continuous.py
physicsnemo/sym/dataset/dataset.py
physicsnemo/sym/dataset/discrete.py
physicsnemo/sym/distributed/__init__.py
physicsnemo/sym/distributed/helpers.py
physicsnemo/sym/distributed/manager.py
physicsnemo/sym/domain/__init__.py
physicsnemo/sym/domain/domain.py
physicsnemo/sym/domain/constraint/__init__.py
physicsnemo/sym/domain/constraint/constraint.py
physicsnemo/sym/domain/constraint/continuous.py
physicsnemo/sym/domain/constraint/discrete.py
physicsnemo/sym/domain/constraint/utils.py
physicsnemo/sym/domain/inferencer/__init__.py
physicsnemo/sym/domain/inferencer/inferencer.py
physicsnemo/sym/domain/inferencer/ov.py
physicsnemo/sym/domain/inferencer/pointwise.py
physicsnemo/sym/domain/inferencer/voxel.py
physicsnemo/sym/domain/inferencer/vtkpointwise.py
physicsnemo/sym/domain/monitor/__init__.py
physicsnemo/sym/domain/monitor/monitor.py
physicsnemo/sym/domain/monitor/pointwise.py
physicsnemo/sym/domain/validator/__init__.py
physicsnemo/sym/domain/validator/continuous.py
physicsnemo/sym/domain/validator/discrete.py
physicsnemo/sym/domain/validator/validator.py
