Metadata-Version: 2.4
Name: nvidia-physicsnemo.sym
Version: 2.3.0
Summary: A deep learning framework for AI-driven multi-physics systems
Author: NVIDIA PhysicsNeMo Team
License: Apache 2.0
Classifier: Programming Language :: Python :: 3
Classifier: License :: OSI Approved :: Apache Software License
Classifier: Operating System :: OS Independent
Requires-Python: >=3.10
License-File: LICENSE.txt
Requires-Dist: Cython>=0.29
Requires-Dist: chaospy>=4.3.7
Requires-Dist: h5py>=3.7.0
Requires-Dist: hydra-core>=1.2.0
Requires-Dist: mistune>=2.0
Requires-Dist: ninja
Requires-Dist: notebook>=7.2.2
Requires-Dist: numpoly<=1.3.4
Requires-Dist: numpy-stl>=2.16
Requires-Dist: nvidia-physicsnemo>=1.0.0
Requires-Dist: opencv-python>=4.8.1.78
Requires-Dist: pillow>=10.3
Requires-Dist: pint>=0.19.2
Requires-Dist: scikit-learn>=1.2.0
Requires-Dist: symengine>=0.10.0
Requires-Dist: sympy>=1.12
Requires-Dist: tensorboard>=2.8.0
Requires-Dist: termcolor>=2.1.1
Requires-Dist: timm>=1.0.3
Requires-Dist: torch-optimizer>=0.3.0
Requires-Dist: transforms3d>=0.3.1
Requires-Dist: typing<3.8,>=3.7
Requires-Dist: vtk>=9.2.6
Dynamic: license-file
